odoo/addons/web_editor_disable_convert_inline/LICENSE
odoo/addons/web_editor_disable_convert_inline/README.rst
odoo/addons/web_editor_disable_convert_inline/__init__.py
odoo/addons/web_editor_disable_convert_inline/__manifest__.py
odoo/addons/web_editor_disable_convert_inline/images/screen.png
odoo/addons/web_editor_disable_convert_inline/static/description/icon.png
odoo/addons/web_editor_disable_convert_inline/static/description/index.html
odoo/addons/web_editor_disable_convert_inline/static/src/js/backend/html_field.esm.js
odoo/addons/web_editor_disable_convert_inline/tests/TEST_INSTRUCTIONS.rst
odoo_addon_web_editor_disable_convert_inline-16.0.1.0.0.dist-info/METADATA
odoo_addon_web_editor_disable_convert_inline-16.0.1.0.0.dist-info/WHEEL
odoo_addon_web_editor_disable_convert_inline-16.0.1.0.0.dist-info/top_level.txt
odoo_addon_web_editor_disable_convert_inline-16.0.1.0.0.dist-info/RECORD
